flapjack/__init__.py
flapjack/flapjack.py
flapjack/simulator.py
flapjack/util.py
pyflapjack-1.0.14.dist-info/licenses/LICENSE
pyflapjack-1.0.14.dist-info/METADATA
pyflapjack-1.0.14.dist-info/WHEEL
pyflapjack-1.0.14.dist-info/top_level.txt
pyflapjack-1.0.14.dist-info/RECORD
