Metadata-Version: 2.4
Name: pyflapjack
Version: 1.0.14
Summary: Python package that interfaces the Flapjack API
Author-email: Timothy Rudge <tim.rudge@ncl.ac.uk>, Gonzalo Vidal <g.a.vidal-pena2@ncl.ac.uk>
Maintainer-email: Gonzalo Vidal <g.a.vidal-pena2@ncl.ac.uk>
License: MIT License
Project-URL: Homepage, https://github.com/RudgeLab/pyFlapjack
Project-URL: Bug Tracker, https://github.com/RudgeLab/pyFlapjack/issues
Keywords: flapjack,data,experimental,analysis,synthetic biology
Classifier: Programming Language :: Python :: 3
Classifier: License :: OSI Approved :: MIT License
Classifier: Operating System :: OS Independent
Requires-Python: <3.11,>=3.7
License-File: LICENSE
Requires-Dist: numpy==1.26.1
Requires-Dist: scipy==1.11.0
Requires-Dist: pandas==1.3.3
Requires-Dist: requests>=2.25.1
Requires-Dist: tqdm==4.62.3
Requires-Dist: plotly==5.3.1
Requires-Dist: asyncio==3.4.3
Requires-Dist: nest_asyncio==1.5.1
Requires-Dist: requests_jwt==0.5.3
Requires-Dist: websockets==10.0
Requires-Dist: matplotlib==3.4.3
Requires-Dist: kaleido==0.2.1
Provides-Extra: test
Requires-Dist: pytest<5.0.0; extra == "test"
Requires-Dist: pytest-cov[all]; extra == "test"
Dynamic: license-file
